{"Symbol": "BBSI", "AssetType": "Common Stock", "Name": "Barrett Business Services, Inc", "Description": "Barrett Business Services, Inc. provides business management solutions for small and mid-sized companies in the United States. It develops a management platform that integrates a knowledge-based approach from the management consulting industry with tools from the human resource outsourcing industry. The company offers professional employer services under which it enters into a client services agreement to establish a co-employment relationship with each client company, assuming responsibility for payroll, payroll taxes, workers' compensation coverage, and other administration functions for the client's existing workforce. It also provides staffing and recruiting services, such as on-demand or short-term staffing assignment, contract staffing, direct placement, and long-term or indefinite-term on-site management services. The company serves electronics manufacturers, various light-manufacturing industries, agriculture-based companies, transportation and shipping enterprises, food processors, telecommunications companies, public utilities, general contractors in various construction-related fields, and professional services firms. Barrett Business Services, Inc. was incorporated in 1965 and is headquartered in Vancouver, Washington.", "Exchange": "NASDAQ", "Currency": "USD", "Country": "USA", "Sector": "Industrials", "Industry": "Staffing & Employment Services", "Address": "8100 NE Parkway Drive, Vancouver, WA, United States, 98662", "FullTimeEmployees": "127085", "FiscalYearEnd": "December", "LatestQuarter": "2020-06-30", "MarketCapitalization": "445162464", "EBITDA": "50397000", "PERatio": "9.7406", "PEGRatio": "1.2768", "BookValue": "23.676", "DividendPerShare": "1.2", "DividendYield": "0.0212", "EPS": "5.82", "RevenuePerShareTTM": "121.499", "ProfitMargin": "0.049", "OperatingMarginTTM": "0.0507", "ReturnOnAssetsTTM": "0.036", "ReturnOnEquityTTM": "0.2823", "RevenueTTM": "913249024", "GrossProfitTTM": "637966000", "DilutedEPSTTM": "5.82", "QuarterlyEarningsGrowthYOY": "-0.166", "QuarterlyRevenueGrowthYOY": "-0.13", "AnalystTargetPrice": "77.5", "TrailingPE": "9.7406", "ForwardPE": "15.3139", "PriceToSalesRatioTTM": "0.478", "PriceToBookRatio": "2.4063", "EVToRevenue": "0.3529", "EVToEBITDA": "5.0867", "Beta": "1.5225", "52WeekHigh": "95.64", "52WeekLow": "27.25", "50DayMovingAverage": "56.5108", "200DayMovingAverage": "51.7278", "SharesOutstanding": "7635720", "SharesFloat": "7248974", "SharesShort": "118681", "SharesShortPriorMonth": "73577", "ShortRatio": "1.42", "ShortPercentOutstanding": "0.01", "ShortPercentFloat": "0.0117", "PercentInsiders": "4.584", "PercentInstitutions": "82.717", "ForwardAnnualDividendRate": "1.2", "ForwardAnnualDividendYield": "0.0212", "PayoutRatio": "0.2062", "DividendDate": "2020-09-04", "ExDividendDate": "2020-08-20", "LastSplitFactor": "1:2", "LastSplitDate": "2013-12-05"}