{"symbol": "HSIC", "annualReports": [{"fiscalDateEnding": "2019-12-31", "reportedCurrency": "USD", "totalAssets": "7151101000", "intangibleAssets": "572878000", "earningAssets": "None", "otherCurrentAssets": "551457000", "totalLiabilities": "3233706000", "totalShareholderEquity": "2998044000", "deferredLongTermLiabilities": "64989000", "otherCurrentLiabilities": "593902000", "commonStock": "1434000", "retainedEarnings": "3116215000", "otherLiabilities": "396162000", "goodwill": "2462495000", "otherAssets": "120811000", "cash": "106097000", "totalCurrentLiabilities": "2038369000", "shortTermDebt": "133824000", "currentLongTermDebt": "133824000", "otherShareholderEquity": "-167373000", "propertyPlantEquipment": "329645000", "totalCurrentAssets": "3226502000", "longTermInvestments": "327919000", "netTangibleAssets": "249929000", "shortTermInvestments": "None", "netReceivables": "1246246000", "longTermDebt": "622908000", "inventory": "1428799000", "accountsPayable": "1310643000", "totalPermanentEquity": "None", "additionalPaidInCapital": "None", "commonStockTotalEquity": "1434000", "preferredStockTotalEquity": "None", "retainedEarningsTotalEquity": "3116215000", "treasuryStock": "None", "accumulatedAmortization": "None", "otherNonCurrrentAssets": "231662000", "deferredLongTermAssetCharges": "None", "totalNonCurrentAssets": "3924599000", "capitalLeaseObligations": "241616000", "totalLongTermDebt": "622908000", "otherNonCurrentLiabilities": "507440000", "totalNonCurrentLiabilities": "1195337000", "negativeGoodwill": "None", "warrants": "287258000", "preferredStockRedeemable": "None", "capitalSurplus": "47768000", "liabilitiesAndShareholderEquity": "7151101000", "cashAndShortTermInvestments": "106097000", "accumulatedDepreciation": "None", "commonStockSharesOutstanding": "143353459"}, {"fiscalDateEnding": "2018-12-31", "reportedCurrency": "USD", "totalAssets": "8500527000", "intangibleAssets": "584244000", "earningAssets": "None", "otherCurrentAssets": "520558000", "totalLiabilities": "4646583000", "totalShareholderEquity": "2961332000", "deferredLongTermLiabilities": "31570000", "otherCurrentLiabilities": "579276000", "commonStock": "1514000", "retainedEarnings": "3208589000", "otherLiabilities": "447412000", "goodwill": "2820295000", "otherAssets": "1254831000", "cash": "80209000", "totalCurrentLiabilities": "3218827000", "shortTermDebt": "960413000", "currentLongTermDebt": "960413000", "otherShareholderEquity": "-248771000", "propertyPlantEquipment": "382398000", "totalCurrentAssets": "4175220000", "longTermInvestments": "538370000", "netTangibleAssets": "-131051000", "shortTermInvestments": "None", "netReceivables": "1603711000", "longTermDebt": "1003873000", "inventory": "1970742000", "accountsPayable": "1679138000", "totalPermanentEquity": "None", "additionalPaidInCapital": "None", "commonStockTotalEquity": "1514000", "preferredStockTotalEquity": "None", "retainedEarningsTotalEquity": "3208589000", "treasuryStock": "None", "accumulatedAmortization": "None", "otherNonCurrrentAssets": "64733000", "deferredLongTermAssetCharges": "None", "totalNonCurrentAssets": "4325307000", "capitalLeaseObligations": "None", "totalLongTermDebt": "1003873000", "otherNonCurrentLiabilities": "392313000", "totalNonCurrentLiabilities": "1427756000", "negativeGoodwill": "None", "warrants": "312156000", "preferredStockRedeemable": "None", "capitalSurplus": "None", "liabilitiesAndShareholderEquity": "8500527000", "cashAndShortTermInvestments": "80209000", "accumulatedDepreciation": "None", "commonStockSharesOutstanding": "151401668"}, {"fiscalDateEnding": "2018-02-21", "reportedCurrency": "USD", "totalAssets": "0", "intangibleAssets": "0", "earningAssets": "None", "otherCurrentAssets": "None", "totalLiabilities": "0", "totalShareholderEquity": "0", "deferredLongTermLiabilities": "0", "otherCurrentLiabilities": "None", "commonStock": "0", "retainedEarnings": "0", "otherLiabilities": "None", "goodwill": "0", "otherAssets": "0", "cash": "0", "totalCurrentLiabilities": "0", "shortTermDebt": "None", "currentLongTermDebt": "None", "otherShareholderEquity": "None", "propertyPlantEquipment": "0", "totalCurrentAssets": "0", "longTermInvestments": "None", "netTangibleAssets": "None", "shortTermInvestments": "0", "netReceivables": "None", "longTermDebt": "0", "inventory": "0", "accountsPayable": "0", "totalPermanentEquity": "0", "additionalPaidInCapital": "0", "commonStockTotalEquity": "1680000", "preferredStockTotalEquity": "0", "retainedEarningsTotalEquity": "2981777000", "treasuryStock": "0", "accumulatedAmortization": "None", "otherNonCurrrentAssets": "None", "deferredLongTermAssetCharges": "None", "totalNonCurrentAssets": "None", "capitalLeaseObligations": "None", "totalLongTermDebt": "None", "otherNonCurrentLiabilities": "None", "totalNonCurrentLiabilities": "None", "negativeGoodwill": "None", "warrants": "None", "preferredStockRedeemable": "None", "capitalSurplus": "None", "liabilitiesAndShareholderEquity": "None", "cashAndShortTermInvestments": "None", "accumulatedDepreciation": "None", "commonStockSharesOutstanding": "None"}, {"fiscalDateEnding": "2017-12-31", "reportedCurrency": "USD", "totalAssets": "7811235000", "intangibleAssets": "669641000", "earningAssets": "None", "otherCurrentAssets": "454752000", "totalLiabilities": "4154687000", "totalShareholderEquity": "2811499000", "deferredLongTermLiabilities": "50431000", "otherCurrentLiabilities": "403020000", "commonStock": "1537000", "retainedEarnings": "2940029000", "otherLiabilities": "470716000", "goodwill": "2301331000", "otherAssets": "126901000", "cash": "174658000", "totalCurrentLiabilities": "2776215000", "shortTermDebt": "758312000", "currentLongTermDebt": "758312000", "otherShareholderEquity": "-130067000", "propertyPlantEquipment": "375001000", "totalCurrentAssets": "4033260000", "longTermInvestments": "432002000", "netTangibleAssets": "672665000", "shortTermInvestments": "None", "netReceivables": "1470047000", "longTermDebt": "907756000", "inventory": "1933803000", "accountsPayable": "1614883000", "totalPermanentEquity": "None", "additionalPaidInCapital": "None", "commonStockTotalEquity": "1537000", "preferredStockTotalEquity": "None", "retainedEarningsTotalEquity": "2940029000", "treasuryStock": "None", "accumulatedAmortization": "None", "otherNonCurrrentAssets": "80924000", "deferredLongTermAssetCharges": "None", "totalNonCurrentAssets": "3777975000", "capitalLeaseObligations": "None", "totalLongTermDebt": "907756000", "otherNonCurrentLiabilities": "420285000", "totalNonCurrentLiabilities": "1378472000", "negativeGoodwill": "None", "warrants": "832138000", "preferredStockRedeemable": "None", "capitalSurplus": "None", "liabilitiesAndShareholderEquity": "7811235000", "cashAndShortTermInvestments": "174658000", "accumulatedDepreciation": "None", "commonStockSharesOutstanding": "153690146"}, {"fiscalDateEnding": "2016-12-31", "reportedCurrency": "USD", "totalAssets": "6730396000", "intangibleAssets": "621180000", "earningAssets": "None", "otherCurrentAssets": "360510000", "totalLiabilities": "3321956000", "totalShareholderEquity": "2793066000", "deferredLongTermLiabilities": "51589000", "otherCurrentLiabilities": "391785000", "commonStock": "794000", "retainedEarnings": "2981777000", "otherLiabilities": "315853000", "goodwill": "2019740000", "otherAssets": "109283000", "cash": "62381000", "totalCurrentLiabilities": "2290646000", "shortTermDebt": "503399000", "currentLongTermDebt": "503399000", "otherShareholderEquity": "-317041000", "propertyPlantEquipment": "333906000", "totalCurrentAssets": "3312780000", "longTermInvestments": "442790000", "netTangibleAssets": "759782000", "shortTermInvestments": "0", "netReceivables": "1254139000", "longTermDebt": "715457000", "inventory": "1635750000", "accountsPayable": "1395462000", "totalPermanentEquity": "0", "additionalPaidInCapital": "207374000", "commonStockTotalEquity": "794000", "preferredStockTotalEquity": "0", "retainedEarningsTotalEquity": "2981777000", "treasuryStock": "0", "accumulatedAmortization": "None", "otherNonCurrrentAssets": "65106000", "deferredLongTermAssetCharges": "None", "totalNonCurrentAssets": "3417616000", "capitalLeaseObligations": "None", "totalLongTermDebt": "715457000", "otherNonCurrentLiabilities": "264264000", "totalNonCurrentLiabilities": "1031310000", "negativeGoodwill": "None", "warrants": "607636000", "preferredStockRedeemable": "None", "capitalSurplus": "127536000", "liabilitiesAndShareholderEquity": "6730396000", "cashAndShortTermInvestments": "62381000", "accumulatedDepreciation": "None", "commonStockSharesOutstanding": "79402505"}], "quarterlyReports": [{"fiscalDateEnding": "2020-06-30", "reportedCurrency": "USD", "totalAssets": "7318125000", "intangibleAssets": "527875000", "earningAssets": "None", "otherCurrentAssets": "901286000", "totalLiabilities": "3417355000", "totalShareholderEquity": "2991087000", "deferredLongTermLiabilities": "56925000", "otherCurrentLiabilities": "536902000", "commonStock": "1424000", "retainedEarnings": "3172439000", "otherLiabilities": "430970000", "goodwill": "2471108000", "otherAssets": "None", "cash": "296110000", "totalCurrentLiabilities": "2307241000", "shortTermDebt": "612765000", "currentLongTermDebt": "612765000", "otherShareholderEquity": "-199251000", "propertyPlantEquipment": "335898000", "totalCurrentAssets": "3409206000", "longTermInvestments": "362565000", "netTangibleAssets": "271329000", "shortTermInvestments": "None", "netReceivables": "1101201000", "longTermDebt": "515802000", "inventory": "1406719000", "accountsPayable": "1157574000", "totalPermanentEquity": "None", "additionalPaidInCapital": "None", "commonStockTotalEquity": "1424000", "preferredStockTotalEquity": "None", "retainedEarningsTotalEquity": "3172439000", "treasuryStock": "None", "accumulatedAmortization": "None", "otherNonCurrrentAssets": "211473000", "deferredLongTermAssetCharges": "None", "totalNonCurrentAssets": "3908919000", "capitalLeaseObligations": "225052000", "totalLongTermDebt": "515802000", "otherNonCurrentLiabilities": "537387000", "totalNonCurrentLiabilities": "1110114000", "negativeGoodwill": "None", "warrants": "279225000", "preferredStockRedeemable": "None", "capitalSurplus": "16475000", "liabilitiesAndShareholderEquity": "7318125000", "cashAndShortTermInvestments": "None", "accumulatedDepreciation": "None", "commonStockSharesOutstanding": "142438127"}, {"fiscalDateEnding": "2020-03-31", "reportedCurrency": "USD", "totalAssets": "7519200000", "intangibleAssets": "554747000", "earningAssets": "None", "otherCurrentAssets": "1091957000", "totalLiabilities": "3641282000", "totalShareholderEquity": "2974577000", "deferredLongTermLiabilities": "73225000", "otherCurrentLiabilities": "554970000", "commonStock": "1424000", "retainedEarnings": "3183236000", "otherLiabilities": "406646000", "goodwill": "2470603000", "otherAssets": "None", "cash": "617368000", "totalCurrentLiabilities": "2205834000", "shortTermDebt": "491406000", "currentLongTermDebt": "491406000", "otherShareholderEquity": "-227648000", "propertyPlantEquipment": "328033000", "totalCurrentAssets": "3619105000", "longTermInvestments": "331590000", "netTangibleAssets": "221353000", "shortTermInvestments": "None", "netReceivables": "1198743000", "longTermDebt": "865821000", "inventory": "1328405000", "accountsPayable": "1159458000", "totalPermanentEquity": "None", "additionalPaidInCapital": "None", "commonStockTotalEquity": "1424000", "preferredStockTotalEquity": "None", "retainedEarningsTotalEquity": "3183236000", "treasuryStock": "None", "accumulatedAmortization": "None", "otherNonCurrrentAssets": "215122000", "deferredLongTermAssetCharges": "None", "totalNonCurrentAssets": "3900095000", "capitalLeaseObligations": "226131000", "totalLongTermDebt": "865821000", "otherNonCurrentLiabilities": "496402000", "totalNonCurrentLiabilities": "1435448000", "negativeGoodwill": "None", "warrants": "272126000", "preferredStockRedeemable": "None", "capitalSurplus": "17565000", "liabilitiesAndShareholderEquity": "7519200000", "cashAndShortTermInvestments": "617368000", "accumulatedDepreciation": "None", "commonStockSharesOutstanding": "142433360"}, {"fiscalDateEnding": "2019-12-31", "reportedCurrency": "USD", "totalAssets": "7151101000", "intangibleAssets": "572878000", "earningAssets": "None", "otherCurrentAssets": "551457000", "totalLiabilities": "3233706000", "totalShareholderEquity": "2998044000", "deferredLongTermLiabilities": "64989000", "otherCurrentLiabilities": "593902000", "commonStock": "1434000", "retainedEarnings": "3116215000", "otherLiabilities": "396162000", "goodwill": "2462495000", "otherAssets": "120811000", "cash": "106097000", "totalCurrentLiabilities": "2038369000", "shortTermDebt": "133824000", "currentLongTermDebt": "133824000", "otherShareholderEquity": "-167373000", "propertyPlantEquipment": "329645000", "totalCurrentAssets": "3226502000", "longTermInvestments": "327919000", "netTangibleAssets": "249929000", "shortTermInvestments": "None", "netReceivables": "1246246000", "longTermDebt": "622908000", "inventory": "1428799000", "accountsPayable": "1310643000", "totalPermanentEquity": "None", "additionalPaidInCapital": "None", "commonStockTotalEquity": "1434000", "preferredStockTotalEquity": "None", "retainedEarningsTotalEquity": "3116215000", "treasuryStock": "None", "accumulatedAmortization": "None", "otherNonCurrrentAssets": "231662000", "deferredLongTermAssetCharges": "None", "totalNonCurrentAssets": "3924599000", "capitalLeaseObligations": "241616000", "totalLongTermDebt": "622908000", "otherNonCurrentLiabilities": "507440000", "totalNonCurrentLiabilities": "1195337000", "negativeGoodwill": "None", "warrants": "287258000", "preferredStockRedeemable": "None", "capitalSurplus": "47768000", "liabilitiesAndShareholderEquity": "7151101000", "cashAndShortTermInvestments": "106097000", "accumulatedDepreciation": "None", "commonStockSharesOutstanding": "143353459"}, {"fiscalDateEnding": "2019-09-30", "reportedCurrency": "USD", "totalAssets": "7097082000", "intangibleAssets": "603172000", "earningAssets": "None", "otherCurrentAssets": "479906000", "totalLiabilities": "3354447000", "totalShareholderEquity": "2829528000", "deferredLongTermLiabilities": "68643000", "otherCurrentLiabilities": "495715000", "commonStock": "1463000", "retainedEarnings": "2957850000", "otherLiabilities": "391021000", "goodwill": "2441175000", "otherAssets": "None", "cash": "75256000", "totalCurrentLiabilities": "1908692000", "shortTermDebt": "217029000", "currentLongTermDebt": "217029000", "otherShareholderEquity": "-195426000", "propertyPlantEquipment": "311123000", "totalCurrentAssets": "3115742000", "longTermInvestments": "385744000", "netTangibleAssets": "68506000", "shortTermInvestments": "None", "netReceivables": "1278939000", "longTermDebt": "872229000", "inventory": "1356897000", "accountsPayable": "1195948000", "totalPermanentEquity": "None", "additionalPaidInCapital": "None", "commonStockTotalEquity": "1463000", "preferredStockTotalEquity": "None", "retainedEarningsTotalEquity": "2957850000", "treasuryStock": "None", "accumulatedAmortization": "None", "otherNonCurrrentAssets": "240126000", "deferredLongTermAssetCharges": "None", "totalNonCurrentAssets": "3981340000", "capitalLeaseObligations": "249879000", "totalLongTermDebt": "872229000", "otherNonCurrentLiabilities": "504883000", "totalNonCurrentLiabilities": "1445755000", "negativeGoodwill": "None", "warrants": "283325000", "preferredStockRedeemable": "None", "capitalSurplus": "65641000", "liabilitiesAndShareholderEquity": "7097082000", "cashAndShortTermInvestments": "75256000", "accumulatedDepreciation": "None", "commonStockSharesOutstanding": "146254864"}, {"fiscalDateEnding": "2019-06-30", "reportedCurrency": "USD", "totalAssets": "7112337000", "intangibleAssets": "631337000", "earningAssets": "None", "otherCurrentAssets": "537273000", "totalLiabilities": "3378409000", "totalShareholderEquity": "2827277000", "deferredLongTermLiabilities": "72177000", "otherCurrentLiabilities": "494569000", "commonStock": "1478000", "retainedEarnings": "2900387000", "otherLiabilities": "401745000", "goodwill": "2431103000", "otherAssets": "None", "cash": "84924000", "totalCurrentLiabilities": "1825277000", "shortTermDebt": "251923000", "currentLongTermDebt": "251923000", "otherShareholderEquity": "-139944000", "propertyPlantEquipment": "315422000", "totalCurrentAssets": "3108714000", "longTermInvestments": "389648000", "netTangibleAssets": "52551000", "shortTermInvestments": "None", "netReceivables": "1203925000", "longTermDebt": "973147000", "inventory": "1367516000", "accountsPayable": "1078785000", "totalPermanentEquity": "None", "additionalPaidInCapital": "None", "commonStockTotalEquity": "1478000", "preferredStockTotalEquity": "None", "retainedEarningsTotalEquity": "2900387000", "treasuryStock": "None", "accumulatedAmortization": "None", "otherNonCurrrentAssets": "236113000", "deferredLongTermAssetCharges": "None", "totalNonCurrentAssets": "4003623000", "capitalLeaseObligations": "246528000", "totalLongTermDebt": "973147000", "otherNonCurrentLiabilities": "507808000", "totalNonCurrentLiabilities": "1553132000", "negativeGoodwill": "None", "warrants": "287714000", "preferredStockRedeemable": "None", "capitalSurplus": "65356000", "liabilitiesAndShareholderEquity": "7112337000", "cashAndShortTermInvestments": "84924000", "accumulatedDepreciation": "None", "commonStockSharesOutstanding": "147823846"}, {"fiscalDateEnding": "2019-03-31", "reportedCurrency": "USD", "totalAssets": "7144864000", "intangibleAssets": "654668000", "earningAssets": "None", "otherCurrentAssets": "457566000", "totalLiabilities": "3443491000", "totalShareholderEquity": "2796922000", "deferredLongTermLiabilities": "76850000", "otherCurrentLiabilities": "502042000", "commonStock": "1490000", "retainedEarnings": "2859182000", "otherLiabilities": "403907000", "goodwill": "2413566000", "otherAssets": "None", "cash": "88115000", "totalCurrentLiabilities": "1878776000", "shortTermDebt": "309031000", "currentLongTermDebt": "309031000", "otherShareholderEquity": "-149878000", "propertyPlantEquipment": "315393000", "totalCurrentAssets": "3109111000", "longTermInvestments": "404004000", "netTangibleAssets": "15388000", "shortTermInvestments": "None", "netReceivables": "1193054000", "longTermDebt": "973500000", "inventory": "1370376000", "accountsPayable": "1067703000", "totalPermanentEquity": "None", "additionalPaidInCapital": "None", "commonStockTotalEquity": "1490000", "preferredStockTotalEquity": "None", "retainedEarningsTotalEquity": "2859182000", "treasuryStock": "None", "accumulatedAmortization": "None", "otherNonCurrrentAssets": "248122000", "deferredLongTermAssetCharges": "None", "totalNonCurrentAssets": "4035753000", "capitalLeaseObligations": "255768000", "totalLongTermDebt": "973500000", "otherNonCurrentLiabilities": "514365000", "totalNonCurrentLiabilities": "1564715000", "negativeGoodwill": "None", "warrants": "286700000", "preferredStockRedeemable": "None", "capitalSurplus": "86128000", "liabilitiesAndShareholderEquity": "7144864000", "cashAndShortTermInvestments": "88115000", "accumulatedDepreciation": "None", "commonStockSharesOutstanding": "148996092"}, {"fiscalDateEnding": "2018-12-31", "reportedCurrency": "USD", "totalAssets": "8500527000", "intangibleAssets": "584244000", "earningAssets": "None", "otherCurrentAssets": "520558000", "totalLiabilities": "4646583000", "totalShareholderEquity": "2961332000", "deferredLongTermLiabilities": "31570000", "otherCurrentLiabilities": "579276000", "commonStock": "1514000", "retainedEarnings": "3208589000", "otherLiabilities": "423883000", "goodwill": "2820295000", "otherAssets": "214627000", "cash": "80209000", "totalCurrentLiabilities": "3218827000", "shortTermDebt": "960413000", "currentLongTermDebt": "7260000", "otherShareholderEquity": "-248771000", "propertyPlantEquipment": "382398000", "totalCurrentAssets": "4175220000", "longTermInvestments": "538370000", "netTangibleAssets": "-131051000", "shortTermInvestments": "None", "netReceivables": "1603711000", "longTermDebt": "1000420000", "inventory": "1970742000", "accountsPayable": "1679138000", "totalPermanentEquity": "None", "additionalPaidInCapital": "None", "commonStockTotalEquity": "1514000", "preferredStockTotalEquity": "None", "retainedEarningsTotalEquity": "3208589000", "treasuryStock": "None", "accumulatedAmortization": "None", "otherNonCurrrentAssets": "None", "deferredLongTermAssetCharges": "None", "totalNonCurrentAssets": "4325307000", "capitalLeaseObligations": "None", "totalLongTermDebt": "1003873000", "otherNonCurrentLiabilities": "392313000", "totalNonCurrentLiabilities": "1427756000", "negativeGoodwill": "None", "warrants": "312156000", "preferredStockRedeemable": "None", "capitalSurplus": "None", "liabilitiesAndShareholderEquity": "8500527000", "cashAndShortTermInvestments": "80209000", "accumulatedDepreciation": "None", "commonStockSharesOutstanding": "151401668"}, {"fiscalDateEnding": "2018-09-30", "reportedCurrency": "USD", "totalAssets": "8390310000", "intangibleAssets": "618201000", "earningAssets": "None", "otherCurrentAssets": "513717000", "totalLiabilities": "4691092000", "totalShareholderEquity": "2973135000", "deferredLongTermLiabilities": "45947000", "otherCurrentLiabilities": "496959000", "commonStock": "1524000", "retainedEarnings": "3191260000", "otherLiabilities": "460992000", "goodwill": "2685681000", "otherAssets": "3822307000", "cash": "119740000", "totalCurrentLiabilities": "3229785000", "shortTermDebt": "1157363000", "currentLongTermDebt": "12482000", "otherShareholderEquity": "-219649000", "propertyPlantEquipment": "374051000", "totalCurrentAssets": "4193952000", "longTermInvestments": "518425000", "netTangibleAssets": "-48245000", "shortTermInvestments": "0", "netReceivables": "1627640000", "longTermDebt": "1000315000", "inventory": "1932855000", "accountsPayable": "1575463000", "totalPermanentEquity": "0", "additionalPaidInCapital": "0", "commonStockTotalEquity": "1524000", "preferredStockTotalEquity": "0", "retainedEarningsTotalEquity": "3191260000", "treasuryStock": "0", "accumulatedAmortization": "None", "otherNonCurrrentAssets": "None", "deferredLongTermAssetCharges": "None", "totalNonCurrentAssets": "4196358000", "capitalLeaseObligations": "None", "totalLongTermDebt": "1000315000", "otherNonCurrentLiabilities": "415045000", "totalNonCurrentLiabilities": "1461307000", "negativeGoodwill": "None", "warrants": "282502000", "preferredStockRedeemable": "None", "capitalSurplus": "None", "liabilitiesAndShareholderEquity": "8390310000", "cashAndShortTermInvestments": "119740000", "accumulatedDepreciation": "None", "commonStockSharesOutstanding": "152437680"}, {"fiscalDateEnding": "2018-08-06", "reportedCurrency": "USD", "totalAssets": "8390310000", "intangibleAssets": "618201000", "earningAssets": "None", "otherCurrentAssets": "513717000", "totalLiabilities": "4691092000", "totalShareholderEquity": "2973135000", "deferredLongTermLiabilities": "45947000", "otherCurrentLiabilities": "496959000", "commonStock": "1524000", "retainedEarnings": "3191260000", "otherLiabilities": "None", "goodwill": "2685681000", "otherAssets": "0", "cash": "119740000", "totalCurrentLiabilities": "3229785000", "shortTermDebt": "1157363000", "currentLongTermDebt": "None", "otherShareholderEquity": "-219649000", "propertyPlantEquipment": "374051000", "totalCurrentAssets": "4193952000", "longTermInvestments": "518425000", "netTangibleAssets": "-48245000", "shortTermInvestments": "0", "netReceivables": "1627640000", "longTermDebt": "0", "inventory": "1932855000", "accountsPayable": "1575463000", "totalPermanentEquity": "0", "additionalPaidInCapital": "0", "commonStockTotalEquity": "1532000", "preferredStockTotalEquity": "0", "retainedEarningsTotalEquity": "2940029000", "treasuryStock": "0", "accumulatedAmortization": "None", "otherNonCurrrentAssets": "None", "deferredLongTermAssetCharges": "None", "totalNonCurrentAssets": "4196358000", "capitalLeaseObligations": "None", "totalLongTermDebt": "1000315000", "otherNonCurrentLiabilities": "415045000", "totalNonCurrentLiabilities": "1461307000", "negativeGoodwill": "None", "warrants": "282502000", "preferredStockRedeemable": "None", "capitalSurplus": "None", "liabilitiesAndShareholderEquity": "8390310000", "cashAndShortTermInvestments": "119740000", "accumulatedDepreciation": "None", "commonStockSharesOutstanding": "None"}, {"fiscalDateEnding": "2018-06-30", "reportedCurrency": "USD", "totalAssets": "7809786000", "intangibleAssets": "612857000", "earningAssets": "None", "otherCurrentAssets": "459320000", "totalLiabilities": "4593891000", "totalShareholderEquity": "2913538000", "deferredLongTermLiabilities": "48126000", "otherCurrentLiabilities": "419199000", "commonStock": "1532000", "retainedEarnings": "3123398000", "otherLiabilities": "455584000", "goodwill": "2255932000", "otherAssets": "3379242000", "cash": "111321000", "totalCurrentLiabilities": "3152922000", "shortTermDebt": "1191809000", "currentLongTermDebt": "12475000", "otherShareholderEquity": "-211392000", "propertyPlantEquipment": "368604000", "totalCurrentAssets": "4061940000", "longTermInvestments": "510453000", "netTangibleAssets": "337735000", "shortTermInvestments": "None", "netReceivables": "1561097000", "longTermDebt": "985385000", "inventory": "1930202000", "accountsPayable": "1541914000", "totalPermanentEquity": "None", "additionalPaidInCapital": "None", "commonStockTotalEquity": "1532000", "preferredStockTotalEquity": "None", "retainedEarningsTotalEquity": "3123398000", "treasuryStock": "None", "accumulatedAmortization": "None", "otherNonCurrrentAssets": "None", "deferredLongTermAssetCharges": "None", "totalNonCurrentAssets": "3747846000", "capitalLeaseObligations": "None", "totalLongTermDebt": "985385000", "otherNonCurrentLiabilities": "407458000", "totalNonCurrentLiabilities": "1440969000", "negativeGoodwill": "None", "warrants": "292986000", "preferredStockRedeemable": "None", "capitalSurplus": "None", "liabilitiesAndShareholderEquity": "7809786000", "cashAndShortTermInvestments": "111321000", "accumulatedDepreciation": "None", "commonStockSharesOutstanding": "153231669"}, {"fiscalDateEnding": "2018-05-08", "reportedCurrency": "USD", "totalAssets": "7809786000", "intangibleAssets": "612857000", "earningAssets": "None", "otherCurrentAssets": "459320000", "totalLiabilities": "4593891000", "totalShareholderEquity": "2913538000", "deferredLongTermLiabilities": "48126000", "otherCurrentLiabilities": "419199000", "commonStock": "1532000", "retainedEarnings": "3123398000", "otherLiabilities": "None", "goodwill": "2255932000", "otherAssets": "0", "cash": "111321000", "totalCurrentLiabilities": "3152922000", "shortTermDebt": "1191809000", "currentLongTermDebt": "None", "otherShareholderEquity": "-211392000", "propertyPlantEquipment": "368604000", "totalCurrentAssets": "4061940000", "longTermInvestments": "510453000", "netTangibleAssets": "337735000", "shortTermInvestments": "0", "netReceivables": "1561097000", "longTermDebt": "0", "inventory": "1930202000", "accountsPayable": "1541914000", "totalPermanentEquity": "0", "additionalPaidInCapital": "0", "commonStockTotalEquity": "1540000", "preferredStockTotalEquity": "0", "retainedEarningsTotalEquity": "2998328000", "treasuryStock": "0", "accumulatedAmortization": "None", "otherNonCurrrentAssets": "None", "deferredLongTermAssetCharges": "None", "totalNonCurrentAssets": "3747846000", "capitalLeaseObligations": "None", "totalLongTermDebt": "985385000", "otherNonCurrentLiabilities": "407458000", "totalNonCurrentLiabilities": "1440969000", "negativeGoodwill": "None", "warrants": "292986000", "preferredStockRedeemable": "None", "capitalSurplus": "None", "liabilitiesAndShareholderEquity": "7809786000", "cashAndShortTermInvestments": "111321000", "accumulatedDepreciation": "None", "commonStockSharesOutstanding": "None"}, {"fiscalDateEnding": "2018-03-31", "reportedCurrency": "USD", "totalAssets": "7914876000", "intangibleAssets": "649465000", "earningAssets": "None", "otherCurrentAssets": "430111000", "totalLiabilities": "4332943000", "totalShareholderEquity": "2901980000", "deferredLongTermLiabilities": "54453000", "otherCurrentLiabilities": "418167000", "commonStock": "1540000", "retainedEarnings": "2998328000", "otherLiabilities": "476137000", "goodwill": "2317873000", "otherAssets": "3417069000", "cash": "99235000", "totalCurrentLiabilities": "2856291000", "shortTermDebt": "968304000", "currentLongTermDebt": "14164000", "otherShareholderEquity": "-97888000", "propertyPlantEquipment": "377002000", "totalCurrentAssets": "4120805000", "longTermInvestments": "449731000", "netTangibleAssets": "604659000", "shortTermInvestments": "None", "netReceivables": "1576390000", "longTermDebt": "1000515000", "inventory": "2015069000", "accountsPayable": "1469820000", "totalPermanentEquity": "None", "additionalPaidInCapital": "None", "commonStockTotalEquity": "1540000", "preferredStockTotalEquity": "None", "retainedEarningsTotalEquity": "2998328000", "treasuryStock": "None", "accumulatedAmortization": "None", "otherNonCurrrentAssets": "None", "deferredLongTermAssetCharges": "None", "totalNonCurrentAssets": "3794071000", "capitalLeaseObligations": "None", "totalLongTermDebt": "1000515000", "otherNonCurrentLiabilities": "421684000", "totalNonCurrentLiabilities": "1476652000", "negativeGoodwill": "None", "warrants": "670017000", "preferredStockRedeemable": "None", "capitalSurplus": "None", "liabilitiesAndShareholderEquity": "7914876000", "cashAndShortTermInvestments": "99235000", "accumulatedDepreciation": "None", "commonStockSharesOutstanding": "154025003"}, {"fiscalDateEnding": "2018-02-21", "reportedCurrency": "USD", "totalAssets": "7914876000", "intangibleAssets": "649465000", "earningAssets": "None", "otherCurrentAssets": "430111000", "totalLiabilities": "4332943000", "totalShareholderEquity": "2901980000", "deferredLongTermLiabilities": "54453000", "otherCurrentLiabilities": "418167000", "commonStock": "1540000", "retainedEarnings": "2998328000", "otherLiabilities": "None", "goodwill": "2317873000", "otherAssets": "0", "cash": "99235000", "totalCurrentLiabilities": "2856291000", "shortTermDebt": "968304000", "currentLongTermDebt": "None", "otherShareholderEquity": "-97888000", "propertyPlantEquipment": "377002000", "totalCurrentAssets": "4120805000", "longTermInvestments": "449731000", "netTangibleAssets": "604659000", "shortTermInvestments": "0", "netReceivables": "1576390000", "longTermDebt": "0", "inventory": "2015069000", "accountsPayable": "1469820000", "totalPermanentEquity": "0", "additionalPaidInCapital": "0", "commonStockTotalEquity": "1680000", "preferredStockTotalEquity": "0", "retainedEarningsTotalEquity": "2981777000", "treasuryStock": "0", "accumulatedAmortization": "None", "otherNonCurrrentAssets": "None", "deferredLongTermAssetCharges": "None", "totalNonCurrentAssets": "3794071000", "capitalLeaseObligations": "None", "totalLongTermDebt": "1000515000", "otherNonCurrentLiabilities": "421684000", "totalNonCurrentLiabilities": "1476652000", "negativeGoodwill": "None", "warrants": "670017000", "preferredStockRedeemable": "None", "capitalSurplus": "None", "liabilitiesAndShareholderEquity": "7914876000", "cashAndShortTermInvestments": "99235000", "accumulatedDepreciation": "None", "commonStockSharesOutstanding": "None"}, {"fiscalDateEnding": "2017-12-31", "reportedCurrency": "USD", "totalAssets": "7811235000", "intangibleAssets": "669641000", "earningAssets": "None", "otherCurrentAssets": "454752000", "totalLiabilities": "4154687000", "totalShareholderEquity": "2811499000", "deferredLongTermLiabilities": "50431000", "otherCurrentLiabilities": "403020000", "commonStock": "1537000", "retainedEarnings": "2940029000", "otherLiabilities": "420285000", "goodwill": "2301331000", "otherAssets": "3402974000", "cash": "174658000", "totalCurrentLiabilities": "2776215000", "shortTermDebt": "758312000", "currentLongTermDebt": "16659000", "otherShareholderEquity": "-130067000", "propertyPlantEquipment": "375001000", "totalCurrentAssets": "4033260000", "longTermInvestments": "432002000", "netTangibleAssets": "672665000", "shortTermInvestments": "None", "netReceivables": "1470047000", "longTermDebt": "907756000", "inventory": "1933803000", "accountsPayable": "1614883000", "totalPermanentEquity": "None", "additionalPaidInCapital": "None", "commonStockTotalEquity": "1537000", "preferredStockTotalEquity": "None", "retainedEarningsTotalEquity": "2940029000", "treasuryStock": "None", "accumulatedAmortization": "None", "otherNonCurrrentAssets": "None", "deferredLongTermAssetCharges": "None", "totalNonCurrentAssets": "3777975000", "capitalLeaseObligations": "None", "totalLongTermDebt": "907756000", "otherNonCurrentLiabilities": "420285000", "totalNonCurrentLiabilities": "1378472000", "negativeGoodwill": "None", "warrants": "832138000", "preferredStockRedeemable": "None", "capitalSurplus": "None", "liabilitiesAndShareholderEquity": "7811235000", "cashAndShortTermInvestments": "174658000", "accumulatedDepreciation": "None", "commonStockSharesOutstanding": "153690146"}, {"fiscalDateEnding": "2017-11-06", "reportedCurrency": "USD", "totalAssets": "7811235000", "intangibleAssets": "669641000", "earningAssets": "None", "otherCurrentAssets": "454752000", "totalLiabilities": "4154687000", "totalShareholderEquity": "2811499000", "deferredLongTermLiabilities": "50431000", "otherCurrentLiabilities": "403020000", "commonStock": "1537000", "retainedEarnings": "2940029000", "otherLiabilities": "None", "goodwill": "2301331000", "otherAssets": "0", "cash": "174658000", "totalCurrentLiabilities": "2776215000", "shortTermDebt": "758312000", "currentLongTermDebt": "None", "otherShareholderEquity": "-130067000", "propertyPlantEquipment": "375001000", "totalCurrentAssets": "4033260000", "longTermInvestments": "432002000", "netTangibleAssets": "672665000", "shortTermInvestments": "0", "netReceivables": "1470047000", "longTermDebt": "0", "inventory": "1933803000", "accountsPayable": "1614883000", "totalPermanentEquity": "0", "additionalPaidInCapital": "126742000", "commonStockTotalEquity": "1570000", "preferredStockTotalEquity": "0", "retainedEarningsTotalEquity": "2981777000", "treasuryStock": "0", "accumulatedAmortization": "None", "otherNonCurrrentAssets": "None", "deferredLongTermAssetCharges": "None", "totalNonCurrentAssets": "3777975000", "capitalLeaseObligations": "None", "totalLongTermDebt": "907756000", "otherNonCurrentLiabilities": "420285000", "totalNonCurrentLiabilities": "1378472000", "negativeGoodwill": "None", "warrants": "832138000", "preferredStockRedeemable": "None", "capitalSurplus": "None", "liabilitiesAndShareholderEquity": "7811235000", "cashAndShortTermInvestments": "174658000", "accumulatedDepreciation": "None", "commonStockSharesOutstanding": "None"}, {"fiscalDateEnding": "2017-09-30", "reportedCurrency": "USD", "totalAssets": "7486661000", "intangibleAssets": "666997000", "earningAssets": "None", "otherCurrentAssets": "465812000", "totalLiabilities": "3728704000", "totalShareholderEquity": "3011639000", "deferredLongTermLiabilities": "91786000", "otherCurrentLiabilities": "358421000", "commonStock": "1570000", "retainedEarnings": "3164541000", "otherLiabilities": "292179000", "goodwill": "2224657000", "otherAssets": "3342424000", "cash": "79879000", "totalCurrentLiabilities": "2437147000", "shortTermDebt": "649112000", "currentLongTermDebt": "17247000", "otherShareholderEquity": "-154472000", "propertyPlantEquipment": "361708000", "totalCurrentAssets": "3782529000", "longTermInvestments": "450770000", "netTangibleAssets": "857732000", "shortTermInvestments": "None", "netReceivables": "1544582000", "longTermDebt": "907592000", "inventory": "1692256000", "accountsPayable": "1429614000", "totalPermanentEquity": "None", "additionalPaidInCapital": "None", "commonStockTotalEquity": "1570000", "preferredStockTotalEquity": "None", "retainedEarningsTotalEquity": "3164541000", "treasuryStock": "None", "accumulatedAmortization": "None", "otherNonCurrrentAssets": "None", "deferredLongTermAssetCharges": "None", "totalNonCurrentAssets": "3704132000", "capitalLeaseObligations": "None", "totalLongTermDebt": "907592000", "otherNonCurrentLiabilities": "292179000", "totalNonCurrentLiabilities": "1291557000", "negativeGoodwill": "None", "warrants": "737747000", "preferredStockRedeemable": "None", "capitalSurplus": "None", "liabilitiesAndShareholderEquity": "7486661000", "cashAndShortTermInvestments": "79879000", "accumulatedDepreciation": "None", "commonStockSharesOutstanding": "156952738"}, {"fiscalDateEnding": "2017-08-08", "reportedCurrency": "USD", "totalAssets": "7486661000", "intangibleAssets": "666997000", "earningAssets": "None", "otherCurrentAssets": "465812000", "totalLiabilities": "3728704000", "totalShareholderEquity": "3011639000", "deferredLongTermLiabilities": "91786000", "otherCurrentLiabilities": "358421000", "commonStock": "1570000", "retainedEarnings": "3164541000", "otherLiabilities": "None", "goodwill": "2224657000", "otherAssets": "0", "cash": "79879000", "totalCurrentLiabilities": "2437147000", "shortTermDebt": "649112000", "currentLongTermDebt": "None", "otherShareholderEquity": "-154472000", "propertyPlantEquipment": "361708000", "totalCurrentAssets": "3782529000", "longTermInvestments": "450770000", "netTangibleAssets": "857732000", "shortTermInvestments": "0", "netReceivables": "1544582000", "longTermDebt": "0", "inventory": "1692256000", "accountsPayable": "1429614000", "totalPermanentEquity": "0", "additionalPaidInCapital": "127536000", "commonStockTotalEquity": "1570000", "preferredStockTotalEquity": "0", "retainedEarningsTotalEquity": "2981777000", "treasuryStock": "0", "accumulatedAmortization": "None", "otherNonCurrrentAssets": "None", "deferredLongTermAssetCharges": "None", "totalNonCurrentAssets": "3704132000", "capitalLeaseObligations": "None", "totalLongTermDebt": "907592000", "otherNonCurrentLiabilities": "292179000", "totalNonCurrentLiabilities": "1291557000", "negativeGoodwill": "None", "warrants": "737747000", "preferredStockRedeemable": "None", "capitalSurplus": "None", "liabilitiesAndShareholderEquity": "7486661000", "cashAndShortTermInvestments": "79879000", "accumulatedDepreciation": "None", "commonStockSharesOutstanding": "None"}, {"fiscalDateEnding": "2017-06-30", "reportedCurrency": "USD", "totalAssets": "7097456000", "intangibleAssets": "636813000", "earningAssets": "None", "otherCurrentAssets": "412904000", "totalLiabilities": "3415804000", "totalShareholderEquity": "2926255000", "deferredLongTermLiabilities": "89756000", "otherCurrentLiabilities": "353432000", "commonStock": "792000", "retainedEarnings": "3134989000", "otherLiabilities": "288478000", "goodwill": "2172563000", "otherAssets": "3282298000", "cash": "74654000", "totalCurrentLiabilities": "2229945000", "shortTermDebt": "594718000", "currentLongTermDebt": "1402343000", "otherShareholderEquity": "-209526000", "propertyPlantEquipment": "351381000", "totalCurrentAssets": "3463777000", "longTermInvestments": "472922000", "netTangibleAssets": "863901000", "shortTermInvestments": "None", "netReceivables": "1409060000", "longTermDebt": "807625000", "inventory": "1567159000", "accountsPayable": "1281795000", "totalPermanentEquity": "None", "additionalPaidInCapital": "None", "commonStockTotalEquity": "792000", "preferredStockTotalEquity": "None", "retainedEarningsTotalEquity": "3134989000", "treasuryStock": "None", "accumulatedAmortization": "None", "otherNonCurrrentAssets": "None", "deferredLongTermAssetCharges": "None", "totalNonCurrentAssets": "3633679000", "capitalLeaseObligations": "None", "totalLongTermDebt": "807625000", "otherNonCurrentLiabilities": "288478000", "totalNonCurrentLiabilities": "1185859000", "negativeGoodwill": "None", "warrants": "747022000", "preferredStockRedeemable": "None", "capitalSurplus": "None", "liabilitiesAndShareholderEquity": "7097456000", "cashAndShortTermInvestments": "74654000", "accumulatedDepreciation": "None", "commonStockSharesOutstanding": "79194792"}, {"fiscalDateEnding": "2017-05-09", "reportedCurrency": "USD", "totalAssets": "0", "intangibleAssets": "0", "earningAssets": "None", "otherCurrentAssets": "None", "totalLiabilities": "0", "totalShareholderEquity": "0", "deferredLongTermLiabilities": "0", "otherCurrentLiabilities": "None", "commonStock": "0", "retainedEarnings": "0", "otherLiabilities": "None", "goodwill": "0", "otherAssets": "0", "cash": "0", "totalCurrentLiabilities": "0", "shortTermDebt": "None", "currentLongTermDebt": "None", "otherShareholderEquity": "None", "propertyPlantEquipment": "0", "totalCurrentAssets": "0", "longTermInvestments": "None", "netTangibleAssets": "None", "shortTermInvestments": "0", "netReceivables": "None", "longTermDebt": "0", "inventory": "0", "accountsPayable": "0", "totalPermanentEquity": "0", "additionalPaidInCapital": "127536000", "commonStockTotalEquity": "794000", "preferredStockTotalEquity": "0", "retainedEarningsTotalEquity": "3068249000", "treasuryStock": "0", "accumulatedAmortization": "None", "otherNonCurrrentAssets": "None", "deferredLongTermAssetCharges": "None", "totalNonCurrentAssets": "None", "capitalLeaseObligations": "None", "totalLongTermDebt": "None", "otherNonCurrentLiabilities": "None", "totalNonCurrentLiabilities": "None", "negativeGoodwill": "None", "warrants": "None", "preferredStockRedeemable": "None", "capitalSurplus": "None", "liabilitiesAndShareholderEquity": "None", "cashAndShortTermInvestments": "None", "accumulatedDepreciation": "None", "commonStockSharesOutstanding": "None"}, {"fiscalDateEnding": "2017-03-31", "reportedCurrency": "USD", "totalAssets": "6844620000", "intangibleAssets": "599183000", "earningAssets": "None", "otherCurrentAssets": "342554000", "totalLiabilities": "3329836000", "totalShareholderEquity": "2787225000", "deferredLongTermLiabilities": "79107000", "otherCurrentLiabilities": "356426000", "commonStock": "795000", "retainedEarnings": "3068249000", "otherLiabilities": "256875000", "goodwill": "2058687000", "otherAssets": "3115898000", "cash": "62888000", "totalCurrentLiabilities": "2285432000", "shortTermDebt": "690328000", "currentLongTermDebt": "690328000", "otherShareholderEquity": "-281819000", "propertyPlantEquipment": "336465000", "totalCurrentAssets": "3392257000", "longTermInvestments": "458028000", "netTangibleAssets": "848745000", "shortTermInvestments": "None", "netReceivables": "1362832000", "longTermDebt": "708422000", "inventory": "1623983000", "accountsPayable": "1238678000", "totalPermanentEquity": "None", "additionalPaidInCapital": "None", "commonStockTotalEquity": "795000", "preferredStockTotalEquity": "None", "retainedEarningsTotalEquity": "3068249000", "treasuryStock": "None", "accumulatedAmortization": "None", "otherNonCurrrentAssets": "None", "deferredLongTermAssetCharges": "None", "totalNonCurrentAssets": "3452363000", "capitalLeaseObligations": "None", "totalLongTermDebt": "708422000", "otherNonCurrentLiabilities": "256875000", "totalNonCurrentLiabilities": "1044404000", "negativeGoodwill": "None", "warrants": "719390000", "preferredStockRedeemable": "None", "capitalSurplus": "None", "liabilitiesAndShareholderEquity": "6844620000", "cashAndShortTermInvestments": "62888000", "accumulatedDepreciation": "None", "commonStockSharesOutstanding": "79468025"}]}